imdbparser/__init__.py
imdbparser/__main__.py
imdbparser/advancedsearchresult.py
imdbparser/base.py
imdbparser/chart.py
imdbparser/exceptions.py
imdbparser/generateadvancedsearchresult.py
imdbparser/imdb.py
imdbparser/movie.py
imdbparser/person.py
imdbparser/searchresult.py
imdbparser-1.0.22.dist-info/LICENSE
imdbparser-1.0.22.dist-info/METADATA
imdbparser-1.0.22.dist-info/WHEEL
imdbparser-1.0.22.dist-info/top_level.txt
imdbparser-1.0.22.dist-info/RECORD
